akv/__init__.py
akv/secrets.py
akv-0.0.1.dist-info/LICENSE
akv-0.0.1.dist-info/METADATA
akv-0.0.1.dist-info/WHEEL
akv-0.0.1.dist-info/top_level.txt
akv-0.0.1.dist-info/RECORD
