Metadata-Version: 2.1
Name: akv
Version: 0.0.1
Summary: Simple access to Azure Key Vault Secrets
Home-page: https://github.com/casperlehmann/akv
Author: Casper Lehmann
Author-email: casperlehmann@gmail.com
License: UNKNOWN
Platform: UNKNOWN
Classifier: Programming Language :: Python :: 3
Classifier: License :: OSI Approved :: MIT License
Classifier: Operating System :: OS Independent
Requires-Python: >=3.6
Requires-Dist: azure-identity
Requires-Dist: azure-keyvault-secrets
